boom2zoom/__init__.py
boom2zoom/__main__.py
boom2zoom/animation/__init__.py
boom2zoom/animation/animdefs.py
boom2zoom/animation/boom.py
boom2zoom/animation/expanded.py
boom2zoom/animation/problems.py
boom2zoom/data/boom-default-switches.csv
boom2zoom/data/games.csv
boom2zoom/data/texture_digests.txt
boom2zoom/dump.py
boom2zoom/settings.py
boom2zoom/stock/__init__.py
boom2zoom/stock/animated.py
boom2zoom/stock/iwads.py
boom2zoom/stock/switches.py
boom2zoom/textures.py
boom2zoom/type_aliases.py
boom2zoom/utils/__init__.py
boom2zoom/utils/collections.py
boom2zoom/utils/csv_utils.py
boom2zoom/utils/plural.py
boom2zoom-2024.6.29.dist-info/entry_points.txt
boom2zoom-2024.6.29.dist-info/LICENSE
boom2zoom-2024.6.29.dist-info/METADATA
boom2zoom-2024.6.29.dist-info/WHEEL
boom2zoom-2024.6.29.dist-info/RECORD
