Metadata-Version: 2.1
Name: Boom2Zoom
Version: 2024.6.29
Summary: Converts media from a WAD file to modern formats.
License: Unlicense
Author: SuaveSteve
Requires-Python: >=3.12,<4.0
Classifier: License :: OSI Approved
Classifier: Programming Language :: Python :: 3
Classifier: Programming Language :: Python :: 3.12
Requires-Dist: attrs (>=23.2.0,<24.0.0)
Requires-Dist: nuitka (>=2.3.10,<3.0.0)
Requires-Dist: omgifol (>=0.5.1,<0.6.0)
Requires-Dist: pillow (>=10.3.0,<11.0.0)
Requires-Dist: typer (>=0.12.3,<0.13.0)
Requires-Dist: typer-slim (>=0.12.3,<0.13.0)
Requires-Dist: types-Pillow (>=10.2.0.20240415,<11.0.0.0)
Requires-Dist: xxhash (>=3.4.1,<4.0.0)
